decofre/__init__.py
decofre/clusterize.py
decofre/datatools.py
decofre/detmentions.py
decofre/eval.py
decofre/infer.py
decofre/lexicon.py
decofre/libdecofre.py
decofre/main.py
decofre/runners.py
decofre/score.py
decofre/utils.py
decofre/visualize.py
decofre/formats/__init__.py
decofre/formats/avp.py
decofre/formats/raw_text.py
decofre/models/__init__.py
decofre/models/config.py
decofre/models/default.jsonnet
decofre/models/defaults.py
decofre/models/encoders.py
decofre/models/utils.py
decofre/tasks/__init__.py
decofre/tasks/antecedent_scoring.py
decofre/tasks/mention_detection.py
decofre/training/__init__.py
decofre/training/sequential.py
tests/__init__.py
tests/datatools_speedtest.py
tests/test_antecedent_scoring.py
tests/test_libdecofre.py
tests/test_models.py
tests/test_utils.py
decofre-0.7.0.dist-info/LICENCE.md
decofre-0.7.0.dist-info/METADATA
decofre-0.7.0.dist-info/WHEEL
decofre-0.7.0.dist-info/entry_points.txt
decofre-0.7.0.dist-info/top_level.txt
decofre-0.7.0.dist-info/RECORD
