Metadata-Version: 2.1
Name: decofre
Version: 0.7.0
Summary: Neural coreference resolution
Home-page: https://github.com/LoicGrobol/decofre
Author: Loïc Grobol
Author-email: loic.grobol@gmail.com
License: MIT
Keywords: nlp,coreference,neural network
Platform: UNKNOWN
Classifier: License :: OSI Approved :: MIT License
Classifier: Programming Language :: Python :: 3.8
Classifier: Programming Language :: Python :: 3.9
Classifier: Environment :: Console
Requires-Python: >=3.8
License-File: LICENCE.md
Requires-Dist: 2to3
Requires-Dist: beautifulsoup4
Requires-Dist: boltons
Requires-Dist: click
Requires-Dist: click-pathlib
Requires-Dist: docopt-ng (>=0.7)
Requires-Dist: doit
Requires-Dist: fouine
Requires-Dist: GitPython
Requires-Dist: jsonlines
Requires-Dist: lmdb
Requires-Dist: loguru
Requires-Dist: lxml
Requires-Dist: networkx
Requires-Dist: numpy
Requires-Dist: orjson
Requires-Dist: pyjson5
Requires-Dist: pytorch-ignite (<0.5.0,>=0.4.0)
Requires-Dist: requests
Requires-Dist: schema
Requires-Dist: scorch
Requires-Dist: spacy (<4.0.0,>=3.0.0)
Requires-Dist: tensorboardx
Requires-Dist: torch (>=1.4.0)
Requires-Dist: tqdm (>=4.40.0)
Requires-Dist: transformers (>=4.0.0)
Requires-Dist: typing-extensions (>=3.7.4)
Requires-Dist: ujson
Provides-Extra: elmo
Requires-Dist: allennlp ; extra == 'elmo'
Provides-Extra: tests
Requires-Dist: pytest ; extra == 'tests'
Requires-Dist: hypothesis ; extra == 'tests'
